EpicDingMessage/__init__.py
EpicDingMessage/message.py
epic_ding_message-0.0.1.dist-info/METADATA
epic_ding_message-0.0.1.dist-info/WHEEL
epic_ding_message-0.0.1.dist-info/top_level.txt
epic_ding_message-0.0.1.dist-info/RECORD
