Metadata-Version: 2.1
Name: epic-ding-message
Version: 0.0.1
Summary: Use DingDing Api send Msg to DingDing Group
Home-page: https://github.com/zerone40
Author: ZERONE40
Author-email: zerone40@163.com
License: UNKNOWN
Platform: UNKNOWN
Classifier: Programming Language :: Python :: 3
Classifier: License :: OSI Approved :: MIT License
Classifier: Operating System :: OS Independent
Requires-Dist: requests
